MANIFEST.in
README.md
README.rst
setup.py
facebookinsights/__init__.py
facebookinsights/commands.py
facebookinsights/graph.py
facebookinsights/oauth.py
facebookinsights.egg-info/PKG-INFO
facebookinsights.egg-info/SOURCES.txt
facebookinsights.egg-info/dependency_links.txt
facebookinsights.egg-info/entry_points.txt
facebookinsights.egg-info/requires.txt
facebookinsights.egg-info/top_level.txt
facebookinsights/tests/__init__.py
facebookinsights/utils/__init__.py
facebookinsights/utils/api.py
facebookinsights/utils/date.py
facebookinsights/utils/functional.py
facebookinsights/utils/server.py
facebookinsights/utils/url.py