Metadata-Version: 1.1
Name: facebookinsights
Version: 0.1.3
Summary: A wrapper and command-line interface for the Facebook Insights API.
Home-page: UNKNOWN
Author: Stijn Debrouwere
Author-email: stijn@debrouwere.org
License: ISC
Download-URL: http://www.github.com/debrouwere/facebook-insights/tarball/master
Keywords: data analytics api wrapper facebook insights
Platform: UNKNOWN
Classifier: Development Status :: 3 - Alpha
Classifier: Intended Audience :: Developers
Classifier: License :: OSI Approved :: MIT License
Classifier: Operating System :: OS Independent
Classifier: Programming Language :: Python
Classifier: Topic :: Scientific/Engineering :: Information Analysis
